[
null,
{"id":1,"list":[{"code":232,"indent":0,"parameters":[1,0,1,1,12,13,100,101,255,0,5,true]},{"code":232,"indent":0,"parameters":[1,0,1,1,12,13,101,100,255,0,5,true]},{"code":0,"indent":0,"parameters":[]}],"name":"【アニメ】くすぐりアニメ","switchId":2,"trigger":2},
{"id":2,"list":[{"code":111,"indent":0,"parameters":[0,4,0]},{"code":231,"indent":1,"parameters":[31,"セリフ1",1,0,461,153,0,0,0,0]},{"code":0,"indent":1,"parameters":[]},{"code":412,"indent":0,"parameters":[]},{"code":232,"indent":0,"parameters":[31,0,1,0,461,153,100,100,255,0,20,true]},{"code":230,"indent":0,"parameters":[30]},{"code":232,"indent":0,"parameters":[31,0,1,0,461,153,0,0,0,0,10,true]},{"code":235,"indent":0,"parameters":[31]},{"code":111,"indent":0,"parameters":[0,4,0]},{"code":231,"indent":1,"parameters":[32,"セリフ2",1,0,744,337,0,0,0,0]},{"code":0,"indent":1,"parameters":[]},{"code":412,"indent":0,"parameters":[]},{"code":232,"indent":0,"parameters":[32,0,1,0,744,337,100,100,255,0,20,true]},{"code":230,"indent":0,"parameters":[30]},{"code":232,"indent":0,"parameters":[32,0,1,0,744,337,0,0,0,0,10,true]},{"code":235,"indent":0,"parameters":[32]},{"code":111,"indent":0,"parameters":[0,4,0]},{"code":231,"indent":1,"parameters":[33,"セリフ3",1,0,497,461,0,0,0,0]},{"code":0,"indent":1,"parameters":[]},{"code":412,"indent":0,"parameters":[]},{"code":232,"indent":0,"parameters":[33,0,1,0,497,461,100,100,255,0,20,true]},{"code":230,"indent":0,"parameters":[30]},{"code":232,"indent":0,"parameters":[33,0,1,0,497,461,0,0,0,0,10,true]},{"code":235,"indent":0,"parameters":[33]},{"code":0,"indent":0,"parameters":[]}],"name":"セリフ１","switchId":4,"trigger":2},
{"id":3,"list":[{"code":111,"indent":0,"parameters":[0,5,0]},{"code":231,"indent":1,"parameters":[31,"セリフ4",1,0,461,153,0,0,0,0]},{"code":0,"indent":1,"parameters":[]},{"code":412,"indent":0,"parameters":[]},{"code":232,"indent":0,"parameters":[31,0,1,0,461,153,100,100,255,0,20,true]},{"code":230,"indent":0,"parameters":[30]},{"code":232,"indent":0,"parameters":[31,0,1,0,461,153,0,0,0,0,10,true]},{"code":235,"indent":0,"parameters":[31]},{"code":111,"indent":0,"parameters":[0,5,0]},{"code":231,"indent":1,"parameters":[32,"セリフ5",1,0,744,337,0,0,0,0]},{"code":0,"indent":1,"parameters":[]},{"code":412,"indent":0,"parameters":[]},{"code":232,"indent":0,"parameters":[32,0,1,0,744,337,100,100,255,0,20,true]},{"code":230,"indent":0,"parameters":[30]},{"code":232,"indent":0,"parameters":[32,0,1,0,744,337,0,0,0,0,10,true]},{"code":235,"indent":0,"parameters":[32]},{"code":111,"indent":0,"parameters":[0,5,0]},{"code":231,"indent":1,"parameters":[33,"セリフ6",1,0,497,461,0,0,0,0]},{"code":0,"indent":1,"parameters":[]},{"code":412,"indent":0,"parameters":[]},{"code":232,"indent":0,"parameters":[33,0,1,0,497,461,100,100,255,0,20,true]},{"code":230,"indent":0,"parameters":[30]},{"code":232,"indent":0,"parameters":[33,0,1,0,497,461,0,0,0,0,10,true]},{"code":235,"indent":0,"parameters":[33]},{"code":0,"indent":0,"parameters":[]}],"name":"セリフ２","switchId":5,"trigger":2},
{"id":4,"list":[{"code":111,"indent":0,"parameters":[0,6,0]},{"code":231,"indent":1,"parameters":[31,"セリフ7",1,0,461,153,0,0,0,0]},{"code":0,"indent":1,"parameters":[]},{"code":412,"indent":0,"parameters":[]},{"code":232,"indent":0,"parameters":[31,0,1,0,461,153,100,100,255,0,20,true]},{"code":230,"indent":0,"parameters":[30]},{"code":232,"indent":0,"parameters":[31,0,1,0,461,153,0,0,0,0,10,true]},{"code":235,"indent":0,"parameters":[31]},{"code":230,"indent":0,"parameters":[60]},{"code":111,"indent":0,"parameters":[0,6,0]},{"code":231,"indent":1,"parameters":[32,"セリフ8",1,0,744,337,0,0,0,0]},{"code":0,"indent":1,"parameters":[]},{"code":412,"indent":0,"parameters":[]},{"code":232,"indent":0,"parameters":[32,0,1,0,744,337,100,100,255,0,20,true]},{"code":230,"indent":0,"parameters":[30]},{"code":232,"indent":0,"parameters":[32,0,1,0,744,337,0,0,0,0,10,true]},{"code":235,"indent":0,"parameters":[32]},{"code":230,"indent":0,"parameters":[60]},{"code":111,"indent":0,"parameters":[0,6,0]},{"code":231,"indent":1,"parameters":[33,"セリフ9",1,0,497,461,0,0,0,0]},{"code":0,"indent":1,"parameters":[]},{"code":412,"indent":0,"parameters":[]},{"code":232,"indent":0,"parameters":[33,0,1,0,497,461,100,100,255,0,20,true]},{"code":230,"indent":0,"parameters":[30]},{"code":232,"indent":0,"parameters":[33,0,1,0,497,461,0,0,0,0,10,true]},{"code":235,"indent":0,"parameters":[33]},{"code":230,"indent":0,"parameters":[120]},{"code":0,"indent":0,"parameters":[]}],"name":"セリフ３","switchId":6,"trigger":2},
{"id":5,"list":[{"code":232,"indent":0,"parameters":[1,0,1,1,12,13,99,101,255,0,4,true]},{"code":232,"indent":0,"parameters":[1,0,1,1,12,13,100,100,255,0,4,true]},{"code":232,"indent":0,"parameters":[1,0,1,1,12,13,99,101,255,0,4,true]},{"code":232,"indent":0,"parameters":[1,0,1,1,12,13,100,100,255,0,4,true]},{"code":230,"indent":0,"parameters":[90]},{"code":0,"indent":0,"parameters":[]}],"name":"おもらしアニメ","switchId":3,"trigger":2},
{"id":6,"list":[{"code":111,"indent":0,"parameters":[1,15,0,0,0]},{"code":111,"indent":1,"parameters":[1,16,0,0,0]},{"code":122,"indent":2,"parameters":[15,15,0,0,403]},{"code":122,"indent":2,"parameters":[16,16,0,0,113]},{"code":0,"indent":2,"parameters":[]},{"code":412,"indent":1,"parameters":[]},{"code":0,"indent":1,"parameters":[]},{"code":412,"indent":0,"parameters":[]},{"code":356,"indent":0,"parameters":["PA_INIT 8 4 横 3"]},{"code":231,"indent":0,"parameters":[20,"こちょ",0,1,15,16,100,100,255,0]},{"code":356,"indent":0,"parameters":["PA_START_LOOP 20 3 [4,5,4]"]},{"code":356,"indent":0,"parameters":["PA_INIT 8 4 横 3"]},{"code":122,"indent":0,"parameters":[15,15,1,0,250]},{"code":122,"indent":0,"parameters":[16,16,1,0,348]},{"code":231,"indent":0,"parameters":[21,"こちょ",0,1,15,16,100,100,255,0]},{"code":356,"indent":0,"parameters":["PA_START_LOOP 21 3 [4,5,4]"]},{"code":356,"indent":0,"parameters":["PA_INIT 8 4 横 3"]},{"code":122,"indent":0,"parameters":[15,15,1,0,-229]},{"code":122,"indent":0,"parameters":[16,16,1,0,-123]},{"code":231,"indent":0,"parameters":[22,"こちょ",0,1,15,16,100,100,255,0]},{"code":356,"indent":0,"parameters":["PA_START_LOOP 22 3 [4,5,4]"]},{"code":356,"indent":0,"parameters":["PA_INIT 8 4 横 3"]},{"code":122,"indent":0,"parameters":[15,15,1,0,287]},{"code":122,"indent":0,"parameters":[16,16,1,0,-126]},{"code":231,"indent":0,"parameters":[23,"こちょ",0,1,15,16,100,100,255,0]},{"code":356,"indent":0,"parameters":["PA_START_LOOP 23 3 [4,5,4]"]},{"code":122,"indent":0,"parameters":[15,15,0,0,0]},{"code":122,"indent":0,"parameters":[16,16,0,0,0]},{"code":0,"indent":0,"parameters":[]}],"name":"こちょアニメ","switchId":1,"trigger":0},
{"id":7,"list":[{"code":121,"indent":0,"parameters":[2,2,1]},{"code":121,"indent":0,"parameters":[3,3,1]},{"code":121,"indent":0,"parameters":[4,4,1]},{"code":121,"indent":0,"parameters":[5,5,1]},{"code":121,"indent":0,"parameters":[6,6,1]},{"code":235,"indent":0,"parameters":[1]},{"code":235,"indent":0,"parameters":[20]},{"code":235,"indent":0,"parameters":[21]},{"code":235,"indent":0,"parameters":[22]},{"code":235,"indent":0,"parameters":[23]},{"code":235,"indent":0,"parameters":[31]},{"code":235,"indent":0,"parameters":[32]},{"code":235,"indent":0,"parameters":[33]},{"code":356,"indent":0,"parameters":["PA_STOP 1"]},{"code":0,"indent":0,"parameters":[]}],"name":"こちょアニメ停止","switchId":1,"trigger":0},
{"id":8,"list":[{"code":121,"indent":0,"parameters":[10,10,1]},{"code":122,"indent":0,"parameters":[20,20,0,3,5,0,1]},{"code":122,"indent":0,"parameters":[3,3,0,3,5,-1,1]},{"code":111,"indent":0,"parameters":[1,3,1,20,3]},{"code":204,"indent":1,"parameters":[2,1,6]},{"code":0,"indent":1,"parameters":[]},{"code":412,"indent":0,"parameters":[]},{"code":111,"indent":0,"parameters":[0,7,0]},{"code":224,"indent":1,"parameters":[[255,255,255,170],30,false]},{"code":250,"indent":1,"parameters":[{"name":"Parry","volume":90,"pitch":100,"pan":0}]},{"code":121,"indent":1,"parameters":[7,7,1]},{"code":235,"indent":1,"parameters":[3]},{"code":119,"indent":1,"parameters":["skip"]},{"code":0,"indent":1,"parameters":[]},{"code":412,"indent":0,"parameters":[]},{"code":111,"indent":0,"parameters":[1,7,0,0,0]},{"code":122,"indent":1,"parameters":[7,7,0,0,1]},{"code":231,"indent":1,"parameters":[1,"シャノン立ち絵b",1,0,561,428,100,100,255,0]},{"code":205,"indent":1,"parameters":[0,{"list":[{"code":39,"indent":null},{"code":0}],"repeat":false,"skippable":false,"wait":true}]},{"code":505,"indent":1,"parameters":[{"code":39,"indent":null}]},{"code":250,"indent":1,"parameters":[{"name":"Damage5","volume":90,"pitch":100,"pan":0}]},{"code":224,"indent":1,"parameters":[[255,255,255,170],30,false]},{"code":225,"indent":1,"parameters":[9,9,30,true]},{"code":119,"indent":1,"parameters":["skip"]},{"code":0,"indent":1,"parameters":[]},{"code":412,"indent":0,"parameters":[]},{"code":111,"indent":0,"parameters":[1,7,0,1,0]},{"code":122,"indent":1,"parameters":[7,7,0,0,2]},{"code":231,"indent":1,"parameters":[1,"シャノン立ち絵c",1,0,561,428,100,100,255,0]},{"code":322,"indent":1,"parameters":[1,"シャノン",1,"シャノン",0,""]},{"code":205,"indent":1,"parameters":[0,{"list":[{"code":39,"indent":null},{"code":0}],"repeat":false,"skippable":false,"wait":true}]},{"code":505,"indent":1,"parameters":[{"code":39,"indent":null}]},{"code":250,"indent":1,"parameters":[{"name":"Damage5","volume":90,"pitch":100,"pan":0}]},{"code":224,"indent":1,"parameters":[[255,255,255,170],30,false]},{"code":225,"indent":1,"parameters":[9,9,30,true]},{"code":119,"indent":1,"parameters":["skip"]},{"code":0,"indent":1,"parameters":[]},{"code":412,"indent":0,"parameters":[]},{"code":111,"indent":0,"parameters":[1,17,0,0,0]},{"code":122,"indent":1,"parameters":[17,17,0,0,1]},{"code":231,"indent":1,"parameters":[1,"スライムa",1,0,597,314,100,100,255,0]},{"code":122,"indent":1,"parameters":[12,12,0,0,597]},{"code":122,"indent":1,"parameters":[13,13,0,0,314]},{"code":121,"indent":1,"parameters":[2,2,0]},{"code":121,"indent":1,"parameters":[4,4,0]},{"code":117,"indent":1,"parameters":[6]},{"code":205,"indent":1,"parameters":[-1,{"list":[{"code":36,"indent":null},{"code":0}],"repeat":false,"skippable":false,"wait":true}]},{"code":505,"indent":1,"parameters":[{"code":36,"indent":null}]},{"code":212,"indent":1,"parameters":[-1,122,false]},{"code":225,"indent":1,"parameters":[5,9,30,false]},{"code":205,"indent":1,"parameters":[-1,{"list":[{"code":18,"indent":null},{"code":15,"parameters":[10],"indent":null},{"code":16,"indent":null},{"code":15,"parameters":[10],"indent":null},{"code":17,"indent":null},{"code":15,"parameters":[10],"indent":null},{"code":19,"indent":null},{"code":15,"parameters":[10],"indent":null},{"code":0}],"repeat":false,"skippable":false,"wait":true}]},{"code":505,"indent":1,"parameters":[{"code":18,"indent":null}]},{"code":505,"indent":1,"parameters":[{"code":15,"parameters":[10],"indent":null}]},{"code":505,"indent":1,"parameters":[{"code":16,"indent":null}]},{"code":505,"indent":1,"parameters":[{"code":15,"parameters":[10],"indent":null}]},{"code":505,"indent":1,"parameters":[{"code":17,"indent":null}]},{"code":505,"indent":1,"parameters":[{"code":15,"parameters":[10],"indent":null}]},{"code":505,"indent":1,"parameters":[{"code":19,"indent":null}]},{"code":505,"indent":1,"parameters":[{"code":15,"parameters":[10],"indent":null}]},{"code":212,"indent":1,"parameters":[-1,122,false]},{"code":225,"indent":1,"parameters":[5,9,30,false]},{"code":205,"indent":1,"parameters":[-1,{"list":[{"code":18,"indent":null},{"code":15,"parameters":[10],"indent":null},{"code":16,"indent":null},{"code":15,"parameters":[10],"indent":null},{"code":17,"indent":null},{"code":15,"parameters":[10],"indent":null},{"code":19,"indent":null},{"code":15,"parameters":[10],"indent":null},{"code":0}],"repeat":false,"skippable":false,"wait":true}]},{"code":505,"indent":1,"parameters":[{"code":18,"indent":null}]},{"code":505,"indent":1,"parameters":[{"code":15,"parameters":[10],"indent":null}]},{"code":505,"indent":1,"parameters":[{"code":16,"indent":null}]},{"code":505,"indent":1,"parameters":[{"code":15,"parameters":[10],"indent":null}]},{"code":505,"indent":1,"parameters":[{"code":17,"indent":null}]},{"code":505,"indent":1,"parameters":[{"code":15,"parameters":[10],"indent":null}]},{"code":505,"indent":1,"parameters":[{"code":19,"indent":null}]},{"code":505,"indent":1,"parameters":[{"code":15,"parameters":[10],"indent":null}]},{"code":212,"indent":1,"parameters":[-1,122,false]},{"code":225,"indent":1,"parameters":[5,9,30,false]},{"code":205,"indent":1,"parameters":[-1,{"list":[{"code":18,"indent":null},{"code":15,"parameters":[10],"indent":null},{"code":16,"indent":null},{"code":15,"parameters":[10],"indent":null},{"code":17,"indent":null},{"code":15,"parameters":[10],"indent":null},{"code":19,"indent":null},{"code":15,"parameters":[10],"indent":null},{"code":0}],"repeat":false,"skippable":false,"wait":true}]},{"code":505,"indent":1,"parameters":[{"code":18,"indent":null}]},{"code":505,"indent":1,"parameters":[{"code":15,"parameters":[10],"indent":null}]},{"code":505,"indent":1,"parameters":[{"code":16,"indent":null}]},{"code":505,"indent":1,"parameters":[{"code":15,"parameters":[10],"indent":null}]},{"code":505,"indent":1,"parameters":[{"code":17,"indent":null}]},{"code":505,"indent":1,"parameters":[{"code":15,"parameters":[10],"indent":null}]},{"code":505,"indent":1,"parameters":[{"code":19,"indent":null}]},{"code":505,"indent":1,"parameters":[{"code":15,"parameters":[10],"indent":null}]},{"code":212,"indent":1,"parameters":[-1,122,false]},{"code":225,"indent":1,"parameters":[5,9,30,false]},{"code":205,"indent":1,"parameters":[-1,{"list":[{"code":18,"indent":null},{"code":15,"parameters":[10],"indent":null},{"code":16,"indent":null},{"code":15,"parameters":[10],"indent":null},{"code":17,"indent":null},{"code":15,"parameters":[10],"indent":null},{"code":19,"indent":null},{"code":15,"parameters":[10],"indent":null},{"code":0}],"repeat":false,"skippable":false,"wait":true}]},{"code":505,"indent":1,"parameters":[{"code":18,"indent":null}]},{"code":505,"indent":1,"parameters":[{"code":15,"parameters":[10],"indent":null}]},{"code":505,"indent":1,"parameters":[{"code":16,"indent":null}]},{"code":505,"indent":1,"parameters":[{"code":15,"parameters":[10],"indent":null}]},{"code":505,"indent":1,"parameters":[{"code":17,"indent":null}]},{"code":505,"indent":1,"parameters":[{"code":15,"parameters":[10],"indent":null}]},{"code":505,"indent":1,"parameters":[{"code":19,"indent":null}]},{"code":505,"indent":1,"parameters":[{"code":15,"parameters":[10],"indent":null}]},{"code":205,"indent":1,"parameters":[-1,{"list":[{"code":35,"indent":null},{"code":0}],"repeat":false,"skippable":false,"wait":true}]},{"code":505,"indent":1,"parameters":[{"code":35,"indent":null}]},{"code":117,"indent":1,"parameters":[7]},{"code":231,"indent":1,"parameters":[1,"シャノン立ち絵c",1,0,561,428,100,100,255,0]},{"code":250,"indent":1,"parameters":[{"name":"Damage5","volume":90,"pitch":100,"pan":0}]},{"code":119,"indent":1,"parameters":["skip"]},{"code":0,"indent":1,"parameters":[]},{"code":412,"indent":0,"parameters":[]},{"code":111,"indent":0,"parameters":[1,17,0,1,0]},{"code":122,"indent":1,"parameters":[17,17,0,0,0]},{"code":231,"indent":1,"parameters":[1,"スライムb",1,0,597,314,100,100,255,0]},{"code":122,"indent":1,"parameters":[12,12,0,0,597]},{"code":122,"indent":1,"parameters":[13,13,0,0,314]},{"code":121,"indent":1,"parameters":[2,2,0]},{"code":121,"indent":1,"parameters":[5,5,0]},{"code":117,"indent":1,"parameters":[6]},{"code":205,"indent":1,"parameters":[-1,{"list":[{"code":36,"indent":null},{"code":0}],"repeat":false,"skippable":false,"wait":true}]},{"code":505,"indent":1,"parameters":[{"code":36,"indent":null}]},{"code":212,"indent":1,"parameters":[-1,122,false]},{"code":225,"indent":1,"parameters":[5,9,30,false]},{"code":205,"indent":1,"parameters":[-1,{"list":[{"code":18,"indent":null},{"code":15,"parameters":[10],"indent":null},{"code":16,"indent":null},{"code":15,"parameters":[10],"indent":null},{"code":17,"indent":null},{"code":15,"parameters":[10],"indent":null},{"code":19,"indent":null},{"code":15,"parameters":[10],"indent":null},{"code":0}],"repeat":false,"skippable":false,"wait":true}]},{"code":505,"indent":1,"parameters":[{"code":18,"indent":null}]},{"code":505,"indent":1,"parameters":[{"code":15,"parameters":[10],"indent":null}]},{"code":505,"indent":1,"parameters":[{"code":16,"indent":null}]},{"code":505,"indent":1,"parameters":[{"code":15,"parameters":[10],"indent":null}]},{"code":505,"indent":1,"parameters":[{"code":17,"indent":null}]},{"code":505,"indent":1,"parameters":[{"code":15,"parameters":[10],"indent":null}]},{"code":505,"indent":1,"parameters":[{"code":19,"indent":null}]},{"code":505,"indent":1,"parameters":[{"code":15,"parameters":[10],"indent":null}]},{"code":212,"indent":1,"parameters":[-1,122,false]},{"code":225,"indent":1,"parameters":[5,9,30,false]},{"code":205,"indent":1,"parameters":[-1,{"list":[{"code":18,"indent":null},{"code":15,"parameters":[10],"indent":null},{"code":16,"indent":null},{"code":15,"parameters":[10],"indent":null},{"code":17,"indent":null},{"code":15,"parameters":[10],"indent":null},{"code":19,"indent":null},{"code":15,"parameters":[10],"indent":null},{"code":0}],"repeat":false,"skippable":false,"wait":true}]},{"code":505,"indent":1,"parameters":[{"code":18,"indent":null}]},{"code":505,"indent":1,"parameters":[{"code":15,"parameters":[10],"indent":null}]},{"code":505,"indent":1,"parameters":[{"code":16,"indent":null}]},{"code":505,"indent":1,"parameters":[{"code":15,"parameters":[10],"indent":null}]},{"code":505,"indent":1,"parameters":[{"code":17,"indent":null}]},{"code":505,"indent":1,"parameters":[{"code":15,"parameters":[10],"indent":null}]},{"code":505,"indent":1,"parameters":[{"code":19,"indent":null}]},{"code":505,"indent":1,"parameters":[{"code":15,"parameters":[10],"indent":null}]},{"code":212,"indent":1,"parameters":[-1,122,false]},{"code":225,"indent":1,"parameters":[5,9,30,false]},{"code":205,"indent":1,"parameters":[-1,{"list":[{"code":18,"indent":null},{"code":15,"parameters":[10],"indent":null},{"code":16,"indent":null},{"code":15,"parameters":[10],"indent":null},{"code":17,"indent":null},{"code":15,"parameters":[10],"indent":null},{"code":19,"indent":null},{"code":15,"parameters":[10],"indent":null},{"code":0}],"repeat":false,"skippable":false,"wait":true}]},{"code":505,"indent":1,"parameters":[{"code":18,"indent":null}]},{"code":505,"indent":1,"parameters":[{"code":15,"parameters":[10],"indent":null}]},{"code":505,"indent":1,"parameters":[{"code":16,"indent":null}]},{"code":505,"indent":1,"parameters":[{"code":15,"parameters":[10],"indent":null}]},{"code":505,"indent":1,"parameters":[{"code":17,"indent":null}]},{"code":505,"indent":1,"parameters":[{"code":15,"parameters":[10],"indent":null}]},{"code":505,"indent":1,"parameters":[{"code":19,"indent":null}]},{"code":505,"indent":1,"parameters":[{"code":15,"parameters":[10],"indent":null}]},{"code":212,"indent":1,"parameters":[-1,122,false]},{"code":225,"indent":1,"parameters":[5,9,30,false]},{"code":205,"indent":1,"parameters":[-1,{"list":[{"code":18,"indent":null},{"code":15,"parameters":[10],"indent":null},{"code":16,"indent":null},{"code":15,"parameters":[10],"indent":null},{"code":17,"indent":null},{"code":15,"parameters":[10],"indent":null},{"code":19,"indent":null},{"code":15,"parameters":[10],"indent":null},{"code":0}],"repeat":false,"skippable":false,"wait":true}]},{"code":505,"indent":1,"parameters":[{"code":18,"indent":null}]},{"code":505,"indent":1,"parameters":[{"code":15,"parameters":[10],"indent":null}]},{"code":505,"indent":1,"parameters":[{"code":16,"indent":null}]},{"code":505,"indent":1,"parameters":[{"code":15,"parameters":[10],"indent":null}]},{"code":505,"indent":1,"parameters":[{"code":17,"indent":null}]},{"code":505,"indent":1,"parameters":[{"code":15,"parameters":[10],"indent":null}]},{"code":505,"indent":1,"parameters":[{"code":19,"indent":null}]},{"code":505,"indent":1,"parameters":[{"code":15,"parameters":[10],"indent":null}]},{"code":117,"indent":1,"parameters":[7]},{"code":231,"indent":1,"parameters":[1,"スライムc",1,0,597,314,100,100,255,0]},{"code":250,"indent":1,"parameters":[{"name":"Liquid","volume":90,"pitch":100,"pan":0}]},{"code":224,"indent":1,"parameters":[[255,255,255,170],30,false]},{"code":225,"indent":1,"parameters":[5,9,30,false]},{"code":121,"indent":1,"parameters":[3,3,0]},{"code":121,"indent":1,"parameters":[6,6,0]},{"code":205,"indent":1,"parameters":[-1,{"list":[{"code":16,"indent":null},{"code":41,"parameters":["シャノン倒れ",1],"indent":null},{"code":15,"parameters":[360],"indent":null},{"code":0}],"repeat":false,"skippable":false,"wait":true}]},{"code":505,"indent":1,"parameters":[{"code":16,"indent":null}]},{"code":505,"indent":1,"parameters":[{"code":41,"parameters":["シャノン倒れ",1],"indent":null}]},{"code":505,"indent":1,"parameters":[{"code":15,"parameters":[360],"indent":null}]},{"code":117,"indent":1,"parameters":[7]},{"code":205,"indent":1,"parameters":[-1,{"list":[{"code":41,"parameters":["シャノン",1],"indent":null},{"code":19,"indent":0},{"code":35,"indent":null},{"code":0}],"repeat":false,"skippable":false,"wait":true}]},{"code":505,"indent":1,"parameters":[{"code":41,"parameters":["シャノン",1],"indent":null}]},{"code":505,"indent":1,"parameters":[{"code":19,"indent":0}]},{"code":505,"indent":1,"parameters":[{"code":35,"indent":null}]},{"code":231,"indent":1,"parameters":[1,"シャノン立ち絵c",1,0,561,428,100,100,255,0]},{"code":250,"indent":1,"parameters":[{"name":"Damage5","volume":90,"pitch":100,"pan":0}]},{"code":119,"indent":1,"parameters":["skip"]},{"code":0,"indent":1,"parameters":[]},{"code":412,"indent":0,"parameters":[]},{"code":118,"indent":0,"parameters":["skip"]},{"code":121,"indent":0,"parameters":[10,10,0]},{"code":214,"indent":0,"parameters":[]},{"code":0,"indent":0,"parameters":[]}],"name":"スライム","switchId":1,"trigger":0},
{"id":9,"list":[{"code":212,"indent":0,"parameters":[-1,123,false]},{"code":122,"indent":0,"parameters":[8,8,1,0,500]},{"code":356,"indent":0,"parameters":["D_TEXT 配達ポイント \\V[8] 32"]},{"code":231,"indent":0,"parameters":[2,"",1,0,400,29,100,100,255,0]},{"code":214,"indent":0,"parameters":[]},{"code":0,"indent":0,"parameters":[]}],"name":"スコア","switchId":1,"trigger":0},
{"id":10,"list":[{"code":121,"indent":0,"parameters":[10,10,1]},{"code":122,"indent":0,"parameters":[20,20,0,3,5,0,1]},{"code":122,"indent":0,"parameters":[3,3,0,3,5,-1,1]},{"code":111,"indent":0,"parameters":[1,3,1,20,3]},{"code":204,"indent":1,"parameters":[2,1,6]},{"code":0,"indent":1,"parameters":[]},{"code":412,"indent":0,"parameters":[]},{"code":111,"indent":0,"parameters":[0,7,0]},{"code":224,"indent":1,"parameters":[[255,255,255,170],30,false]},{"code":250,"indent":1,"parameters":[{"name":"Parry","volume":90,"pitch":100,"pan":0}]},{"code":121,"indent":1,"parameters":[7,7,1]},{"code":235,"indent":1,"parameters":[3]},{"code":119,"indent":1,"parameters":["skip"]},{"code":0,"indent":1,"parameters":[]},{"code":412,"indent":0,"parameters":[]},{"code":111,"indent":0,"parameters":[1,7,0,0,0]},{"code":122,"indent":1,"parameters":[7,7,0,0,1]},{"code":231,"indent":1,"parameters":[1,"シャノン立ち絵b",1,0,561,428,100,100,255,0]},{"code":205,"indent":1,"parameters":[0,{"list":[{"code":39,"indent":null},{"code":0}],"repeat":false,"skippable":false,"wait":true}]},{"code":505,"indent":1,"parameters":[{"code":39,"indent":null}]},{"code":250,"indent":1,"parameters":[{"name":"Damage5","volume":90,"pitch":100,"pan":0}]},{"code":224,"indent":1,"parameters":[[255,255,255,170],30,false]},{"code":225,"indent":1,"parameters":[9,9,30,true]},{"code":119,"indent":1,"parameters":["skip"]},{"code":0,"indent":1,"parameters":[]},{"code":412,"indent":0,"parameters":[]},{"code":111,"indent":0,"parameters":[1,7,0,1,0]},{"code":122,"indent":1,"parameters":[7,7,0,0,2]},{"code":231,"indent":1,"parameters":[1,"シャノン立ち絵c",1,0,561,428,100,100,255,0]},{"code":322,"indent":1,"parameters":[1,"シャノン",1,"シャノン",0,""]},{"code":205,"indent":1,"parameters":[0,{"list":[{"code":39,"indent":null},{"code":0}],"repeat":false,"skippable":false,"wait":true}]},{"code":505,"indent":1,"parameters":[{"code":39,"indent":null}]},{"code":250,"indent":1,"parameters":[{"name":"Damage5","volume":90,"pitch":100,"pan":0}]},{"code":224,"indent":1,"parameters":[[255,255,255,170],30,false]},{"code":225,"indent":1,"parameters":[9,9,30,true]},{"code":119,"indent":1,"parameters":["skip"]},{"code":0,"indent":1,"parameters":[]},{"code":412,"indent":0,"parameters":[]},{"code":111,"indent":0,"parameters":[1,18,0,0,0]},{"code":122,"indent":1,"parameters":[18,18,0,0,1]},{"code":231,"indent":1,"parameters":[1,"触手a",1,0,597,314,100,100,255,0]},{"code":122,"indent":1,"parameters":[12,12,0,0,597]},{"code":122,"indent":1,"parameters":[13,13,0,0,314]},{"code":121,"indent":1,"parameters":[2,2,0]},{"code":121,"indent":1,"parameters":[4,4,0]},{"code":117,"indent":1,"parameters":[6]},{"code":205,"indent":1,"parameters":[-1,{"list":[{"code":36,"indent":null},{"code":0}],"repeat":false,"skippable":false,"wait":true}]},{"code":505,"indent":1,"parameters":[{"code":36,"indent":null}]},{"code":212,"indent":1,"parameters":[-1,122,false]},{"code":225,"indent":1,"parameters":[5,9,30,false]},{"code":205,"indent":1,"parameters":[-1,{"list":[{"code":18,"indent":null},{"code":15,"parameters":[10],"indent":null},{"code":16,"indent":null},{"code":15,"parameters":[10],"indent":null},{"code":17,"indent":null},{"code":15,"parameters":[10],"indent":null},{"code":19,"indent":null},{"code":15,"parameters":[10],"indent":null},{"code":0}],"repeat":false,"skippable":false,"wait":true}]},{"code":505,"indent":1,"parameters":[{"code":18,"indent":null}]},{"code":505,"indent":1,"parameters":[{"code":15,"parameters":[10],"indent":null}]},{"code":505,"indent":1,"parameters":[{"code":16,"indent":null}]},{"code":505,"indent":1,"parameters":[{"code":15,"parameters":[10],"indent":null}]},{"code":505,"indent":1,"parameters":[{"code":17,"indent":null}]},{"code":505,"indent":1,"parameters":[{"code":15,"parameters":[10],"indent":null}]},{"code":505,"indent":1,"parameters":[{"code":19,"indent":null}]},{"code":505,"indent":1,"parameters":[{"code":15,"parameters":[10],"indent":null}]},{"code":212,"indent":1,"parameters":[-1,122,false]},{"code":225,"indent":1,"parameters":[5,9,30,false]},{"code":205,"indent":1,"parameters":[-1,{"list":[{"code":18,"indent":null},{"code":15,"parameters":[10],"indent":null},{"code":16,"indent":null},{"code":15,"parameters":[10],"indent":null},{"code":17,"indent":null},{"code":15,"parameters":[10],"indent":null},{"code":19,"indent":null},{"code":15,"parameters":[10],"indent":null},{"code":0}],"repeat":false,"skippable":false,"wait":true}]},{"code":505,"indent":1,"parameters":[{"code":18,"indent":null}]},{"code":505,"indent":1,"parameters":[{"code":15,"parameters":[10],"indent":null}]},{"code":505,"indent":1,"parameters":[{"code":16,"indent":null}]},{"code":505,"indent":1,"parameters":[{"code":15,"parameters":[10],"indent":null}]},{"code":505,"indent":1,"parameters":[{"code":17,"indent":null}]},{"code":505,"indent":1,"parameters":[{"code":15,"parameters":[10],"indent":null}]},{"code":505,"indent":1,"parameters":[{"code":19,"indent":null}]},{"code":505,"indent":1,"parameters":[{"code":15,"parameters":[10],"indent":null}]},{"code":212,"indent":1,"parameters":[-1,122,false]},{"code":225,"indent":1,"parameters":[5,9,30,false]},{"code":205,"indent":1,"parameters":[-1,{"list":[{"code":18,"indent":null},{"code":15,"parameters":[10],"indent":null},{"code":16,"indent":null},{"code":15,"parameters":[10],"indent":null},{"code":17,"indent":null},{"code":15,"parameters":[10],"indent":null},{"code":19,"indent":null},{"code":15,"parameters":[10],"indent":null},{"code":0}],"repeat":false,"skippable":false,"wait":true}]},{"code":505,"indent":1,"parameters":[{"code":18,"indent":null}]},{"code":505,"indent":1,"parameters":[{"code":15,"parameters":[10],"indent":null}]},{"code":505,"indent":1,"parameters":[{"code":16,"indent":null}]},{"code":505,"indent":1,"parameters":[{"code":15,"parameters":[10],"indent":null}]},{"code":505,"indent":1,"parameters":[{"code":17,"indent":null}]},{"code":505,"indent":1,"parameters":[{"code":15,"parameters":[10],"indent":null}]},{"code":505,"indent":1,"parameters":[{"code":19,"indent":null}]},{"code":505,"indent":1,"parameters":[{"code":15,"parameters":[10],"indent":null}]},{"code":212,"indent":1,"parameters":[-1,122,false]},{"code":225,"indent":1,"parameters":[5,9,30,false]},{"code":205,"indent":1,"parameters":[-1,{"list":[{"code":18,"indent":null},{"code":15,"parameters":[10],"indent":null},{"code":16,"indent":null},{"code":15,"parameters":[10],"indent":null},{"code":17,"indent":null},{"code":15,"parameters":[10],"indent":null},{"code":19,"indent":null},{"code":15,"parameters":[10],"indent":null},{"code":0}],"repeat":false,"skippable":false,"wait":true}]},{"code":505,"indent":1,"parameters":[{"code":18,"indent":null}]},{"code":505,"indent":1,"parameters":[{"code":15,"parameters":[10],"indent":null}]},{"code":505,"indent":1,"parameters":[{"code":16,"indent":null}]},{"code":505,"indent":1,"parameters":[{"code":15,"parameters":[10],"indent":null}]},{"code":505,"indent":1,"parameters":[{"code":17,"indent":null}]},{"code":505,"indent":1,"parameters":[{"code":15,"parameters":[10],"indent":null}]},{"code":505,"indent":1,"parameters":[{"code":19,"indent":null}]},{"code":505,"indent":1,"parameters":[{"code":15,"parameters":[10],"indent":null}]},{"code":205,"indent":1,"parameters":[-1,{"list":[{"code":35,"indent":null},{"code":0}],"repeat":false,"skippable":false,"wait":true}]},{"code":505,"indent":1,"parameters":[{"code":35,"indent":null}]},{"code":117,"indent":1,"parameters":[7]},{"code":231,"indent":1,"parameters":[1,"シャノン立ち絵c",1,0,561,428,100,100,255,0]},{"code":250,"indent":1,"parameters":[{"name":"Damage5","volume":90,"pitch":100,"pan":0}]},{"code":119,"indent":1,"parameters":["skip"]},{"code":0,"indent":1,"parameters":[]},{"code":412,"indent":0,"parameters":[]},{"code":111,"indent":0,"parameters":[1,18,0,1,0]},{"code":122,"indent":1,"parameters":[18,18,0,0,0]},{"code":231,"indent":1,"parameters":[1,"触手b",1,0,597,314,100,100,255,0]},{"code":122,"indent":1,"parameters":[12,12,0,0,597]},{"code":122,"indent":1,"parameters":[13,13,0,0,314]},{"code":121,"indent":1,"parameters":[2,2,0]},{"code":121,"indent":1,"parameters":[5,5,0]},{"code":117,"indent":1,"parameters":[6]},{"code":205,"indent":1,"parameters":[-1,{"list":[{"code":36,"indent":null},{"code":0}],"repeat":false,"skippable":false,"wait":true}]},{"code":505,"indent":1,"parameters":[{"code":36,"indent":null}]},{"code":212,"indent":1,"parameters":[-1,122,false]},{"code":225,"indent":1,"parameters":[5,9,30,false]},{"code":205,"indent":1,"parameters":[-1,{"list":[{"code":18,"indent":null},{"code":15,"parameters":[10],"indent":null},{"code":16,"indent":null},{"code":15,"parameters":[10],"indent":null},{"code":17,"indent":null},{"code":15,"parameters":[10],"indent":null},{"code":19,"indent":null},{"code":15,"parameters":[10],"indent":null},{"code":0}],"repeat":false,"skippable":false,"wait":true}]},{"code":505,"indent":1,"parameters":[{"code":18,"indent":null}]},{"code":505,"indent":1,"parameters":[{"code":15,"parameters":[10],"indent":null}]},{"code":505,"indent":1,"parameters":[{"code":16,"indent":null}]},{"code":505,"indent":1,"parameters":[{"code":15,"parameters":[10],"indent":null}]},{"code":505,"indent":1,"parameters":[{"code":17,"indent":null}]},{"code":505,"indent":1,"parameters":[{"code":15,"parameters":[10],"indent":null}]},{"code":505,"indent":1,"parameters":[{"code":19,"indent":null}]},{"code":505,"indent":1,"parameters":[{"code":15,"parameters":[10],"indent":null}]},{"code":212,"indent":1,"parameters":[-1,122,false]},{"code":225,"indent":1,"parameters":[5,9,30,false]},{"code":205,"indent":1,"parameters":[-1,{"list":[{"code":18,"indent":null},{"code":15,"parameters":[10],"indent":null},{"code":16,"indent":null},{"code":15,"parameters":[10],"indent":null},{"code":17,"indent":null},{"code":15,"parameters":[10],"indent":null},{"code":19,"indent":null},{"code":15,"parameters":[10],"indent":null},{"code":0}],"repeat":false,"skippable":false,"wait":true}]},{"code":505,"indent":1,"parameters":[{"code":18,"indent":null}]},{"code":505,"indent":1,"parameters":[{"code":15,"parameters":[10],"indent":null}]},{"code":505,"indent":1,"parameters":[{"code":16,"indent":null}]},{"code":505,"indent":1,"parameters":[{"code":15,"parameters":[10],"indent":null}]},{"code":505,"indent":1,"parameters":[{"code":17,"indent":null}]},{"code":505,"indent":1,"parameters":[{"code":15,"parameters":[10],"indent":null}]},{"code":505,"indent":1,"parameters":[{"code":19,"indent":null}]},{"code":505,"indent":1,"parameters":[{"code":15,"parameters":[10],"indent":null}]},{"code":212,"indent":1,"parameters":[-1,122,false]},{"code":225,"indent":1,"parameters":[5,9,30,false]},{"code":205,"indent":1,"parameters":[-1,{"list":[{"code":18,"indent":null},{"code":15,"parameters":[10],"indent":null},{"code":16,"indent":null},{"code":15,"parameters":[10],"indent":null},{"code":17,"indent":null},{"code":15,"parameters":[10],"indent":null},{"code":19,"indent":null},{"code":15,"parameters":[10],"indent":null},{"code":0}],"repeat":false,"skippable":false,"wait":true}]},{"code":505,"indent":1,"parameters":[{"code":18,"indent":null}]},{"code":505,"indent":1,"parameters":[{"code":15,"parameters":[10],"indent":null}]},{"code":505,"indent":1,"parameters":[{"code":16,"indent":null}]},{"code":505,"indent":1,"parameters":[{"code":15,"parameters":[10],"indent":null}]},{"code":505,"indent":1,"parameters":[{"code":17,"indent":null}]},{"code":505,"indent":1,"parameters":[{"code":15,"parameters":[10],"indent":null}]},{"code":505,"indent":1,"parameters":[{"code":19,"indent":null}]},{"code":505,"indent":1,"parameters":[{"code":15,"parameters":[10],"indent":null}]},{"code":212,"indent":1,"parameters":[-1,122,false]},{"code":225,"indent":1,"parameters":[5,9,30,false]},{"code":205,"indent":1,"parameters":[-1,{"list":[{"code":18,"indent":null},{"code":15,"parameters":[10],"indent":null},{"code":16,"indent":null},{"code":15,"parameters":[10],"indent":null},{"code":17,"indent":null},{"code":15,"parameters":[10],"indent":null},{"code":19,"indent":null},{"code":15,"parameters":[10],"indent":null},{"code":0}],"repeat":false,"skippable":false,"wait":true}]},{"code":505,"indent":1,"parameters":[{"code":18,"indent":null}]},{"code":505,"indent":1,"parameters":[{"code":15,"parameters":[10],"indent":null}]},{"code":505,"indent":1,"parameters":[{"code":16,"indent":null}]},{"code":505,"indent":1,"parameters":[{"code":15,"parameters":[10],"indent":null}]},{"code":505,"indent":1,"parameters":[{"code":17,"indent":null}]},{"code":505,"indent":1,"parameters":[{"code":15,"parameters":[10],"indent":null}]},{"code":505,"indent":1,"parameters":[{"code":19,"indent":null}]},{"code":505,"indent":1,"parameters":[{"code":15,"parameters":[10],"indent":null}]},{"code":117,"indent":1,"parameters":[7]},{"code":231,"indent":1,"parameters":[1,"触手c",1,0,597,314,100,100,255,0]},{"code":250,"indent":1,"parameters":[{"name":"Liquid","volume":90,"pitch":100,"pan":0}]},{"code":224,"indent":1,"parameters":[[255,255,255,170],30,false]},{"code":225,"indent":1,"parameters":[5,9,30,false]},{"code":121,"indent":1,"parameters":[3,3,0]},{"code":121,"indent":1,"parameters":[6,6,0]},{"code":205,"indent":1,"parameters":[-1,{"list":[{"code":16,"indent":null},{"code":41,"parameters":["シャノン倒れ",1],"indent":null},{"code":15,"parameters":[360],"indent":null},{"code":0}],"repeat":false,"skippable":false,"wait":true}]},{"code":505,"indent":1,"parameters":[{"code":16,"indent":null}]},{"code":505,"indent":1,"parameters":[{"code":41,"parameters":["シャノン倒れ",1],"indent":null}]},{"code":505,"indent":1,"parameters":[{"code":15,"parameters":[360],"indent":null}]},{"code":117,"indent":1,"parameters":[7]},{"code":205,"indent":1,"parameters":[-1,{"list":[{"code":41,"parameters":["シャノン",1],"indent":null},{"code":19,"indent":0},{"code":35,"indent":null},{"code":0}],"repeat":false,"skippable":false,"wait":true}]},{"code":505,"indent":1,"parameters":[{"code":41,"parameters":["シャノン",1],"indent":null}]},{"code":505,"indent":1,"parameters":[{"code":19,"indent":0}]},{"code":505,"indent":1,"parameters":[{"code":35,"indent":null}]},{"code":231,"indent":1,"parameters":[1,"シャノン立ち絵c",1,0,561,428,100,100,255,0]},{"code":250,"indent":1,"parameters":[{"name":"Damage5","volume":90,"pitch":100,"pan":0}]},{"code":119,"indent":1,"parameters":["skip"]},{"code":0,"indent":1,"parameters":[]},{"code":412,"indent":0,"parameters":[]},{"code":118,"indent":0,"parameters":["skip"]},{"code":121,"indent":0,"parameters":[10,10,0]},{"code":214,"indent":0,"parameters":[]},{"code":0,"indent":0,"parameters":[]}],"name":"触手","switchId":1,"trigger":0},
{"id":11,"list":[{"code":241,"indent":0,"parameters":[{"name":"Theme1","volume":50,"pitch":50,"pan":0}]},{"code":223,"indent":0,"parameters":[[-204,-204,-204,0],10,true]},{"code":231,"indent":0,"parameters":[1,"イベントa",1,0,428,294,100,100,0,0]},{"code":232,"indent":0,"parameters":[1,0,1,0,428,294,100,100,255,0,60,true]},{"code":101,"indent":0,"parameters":["",0,1,2]},{"code":401,"indent":0,"parameters":["次第に晴れていく煙の中から姿を現したのは"]},{"code":401,"indent":0,"parameters":["情けないポーズのまま動けない"]},{"code":401,"indent":0,"parameters":["下着姿のシャノンだった。"]},{"code":101,"indent":0,"parameters":["",0,1,2]},{"code":401,"indent":0,"parameters":["シャノン"]},{"code":401,"indent":0,"parameters":["「なっ！！？\\."]},{"code":401,"indent":0,"parameters":["　なんですかこれっ！！？」"]},{"code":101,"indent":0,"parameters":["",0,1,2]},{"code":401,"indent":0,"parameters":["シャノンは手を頭の後ろに回して、つま先立ちで屈んで"]},{"code":401,"indent":0,"parameters":["股を大開にするという恥ずかしい以外に形容の仕様がない"]},{"code":401,"indent":0,"parameters":["ポーズのままピクリとも動けない。"]},{"code":101,"indent":0,"parameters":["",0,1,2]},{"code":401,"indent":0,"parameters":["シャノンをこんなに恥ずかしい目に合わせたのは"]},{"code":401,"indent":0,"parameters":["ＡＨＡＺＯＮの新製品、ポーズ強制ガス"]},{"code":401,"indent":0,"parameters":["そして、それにブレンドされていた衣類破壊ガスだ。"]},{"code":101,"indent":0,"parameters":["",0,1,2]},{"code":401,"indent":0,"parameters":["シャノン"]},{"code":401,"indent":0,"parameters":["「うぅ……\\.　恥ずかしい……っ\\."]},{"code":401,"indent":0,"parameters":["　いつ終わるんですかこれ……っ」"]},{"code":101,"indent":0,"parameters":["",0,1,2]},{"code":401,"indent":0,"parameters":["顔を真っ赤にしつつも"]},{"code":401,"indent":0,"parameters":["自分ではどうしようもないことを悟って"]},{"code":401,"indent":0,"parameters":["シャノンは効果が切れるまで耐え続ける覚悟を決める。"]},{"code":101,"indent":0,"parameters":["",0,1,2]},{"code":401,"indent":0,"parameters":["だが、不運は重なるもの。"]},{"code":401,"indent":0,"parameters":["荷物の中のトラップは衝撃によって起動するもので"]},{"code":401,"indent":0,"parameters":["先ほどのガス爆発によってそのほとんどが連鎖的に"]},{"code":401,"indent":0,"parameters":["起動してしまう……！"]},{"code":231,"indent":0,"parameters":[1,"イベントb",1,0,428,294,100,100,255,0]},{"code":250,"indent":0,"parameters":[{"name":"Wind3","volume":90,"pitch":100,"pan":0}]},{"code":224,"indent":0,"parameters":[[255,255,255,170],30,false]},{"code":225,"indent":0,"parameters":[9,9,30,false]},{"code":122,"indent":0,"parameters":[12,12,0,0,428]},{"code":122,"indent":0,"parameters":[13,13,0,0,294]},{"code":121,"indent":0,"parameters":[2,2,0]},{"code":122,"indent":0,"parameters":[15,15,0,0,217]},{"code":122,"indent":0,"parameters":[16,16,0,0,96]},{"code":117,"indent":0,"parameters":[6]},{"code":101,"indent":0,"parameters":["",0,1,2]},{"code":401,"indent":0,"parameters":["シャノン"]},{"code":401,"indent":0,"parameters":["「ちょ、\\.何を……っ！！？\\."]},{"code":401,"indent":0,"parameters":["　くひひひひ……っ\\."]},{"code":401,"indent":0,"parameters":["　く、\\.くすぐらないでください……っ！」"]},{"code":101,"indent":0,"parameters":["",0,1,2]},{"code":401,"indent":0,"parameters":["数本の筆はシャノンの身体を舐めるようにねっとりと"]},{"code":401,"indent":0,"parameters":["這いまわり、じわじわとくすぐったさを浸透させていく。"]},{"code":401,"indent":0,"parameters":["決して厳しい責めではないのだが"]},{"code":401,"indent":0,"parameters":["かといって我慢しきれるほど甘いものでもない。"]},{"code":250,"indent":0,"parameters":[{"name":"Wind3","volume":90,"pitch":100,"pan":0}]},{"code":224,"indent":0,"parameters":[[255,255,255,170],30,false]},{"code":225,"indent":0,"parameters":[9,9,30,false]},{"code":101,"indent":0,"parameters":["",0,1,2]},{"code":401,"indent":0,"parameters":["シャノン"]},{"code":401,"indent":0,"parameters":["「ひふふふっ\\.　…………っ！！\\."]},{"code":401,"indent":0,"parameters":["　お、\\.おへそはやめて……っ！\\."]},{"code":401,"indent":0,"parameters":["　あひっ、\\.ひっひひひひひ！」"]},{"code":101,"indent":0,"parameters":["",0,1,2]},{"code":401,"indent":0,"parameters":["起動したトラップは筆だけではない。"]},{"code":401,"indent":0,"parameters":["同時に起動していた数体のマジックハンドが"]},{"code":401,"indent":0,"parameters":["荷物の中から遅れて顔を出し"]},{"code":401,"indent":0,"parameters":["シャノンの体に群がっていく……！"]},{"code":117,"indent":0,"parameters":[7]},{"code":231,"indent":0,"parameters":[1,"イベントc",1,0,428,294,100,100,255,0]},{"code":250,"indent":0,"parameters":[{"name":"Wind3","volume":90,"pitch":100,"pan":0}]},{"code":224,"indent":0,"parameters":[[255,255,255,170],30,false]},{"code":225,"indent":0,"parameters":[9,9,30,false]},{"code":122,"indent":0,"parameters":[12,12,0,0,428]},{"code":122,"indent":0,"parameters":[13,13,0,0,294]},{"code":121,"indent":0,"parameters":[2,2,0]},{"code":122,"indent":0,"parameters":[15,15,0,0,217]},{"code":122,"indent":0,"parameters":[16,16,0,0,96]},{"code":117,"indent":0,"parameters":[6]},{"code":101,"indent":0,"parameters":["",0,1,2]},{"code":401,"indent":0,"parameters":["シャノン"]},{"code":401,"indent":0,"parameters":["「あははははははははは！！？\\."]},{"code":401,"indent":0,"parameters":["　て、\\.手はやめてくださいぃぃぃっひひひひ！！\\."]},{"code":401,"indent":0,"parameters":["　ま、\\.まさかっ、\\.荷物全部……っ！！？」"]},{"code":101,"indent":0,"parameters":["",0,1,2]},{"code":401,"indent":0,"parameters":["マジックハンドのくすぐりは筆のそれとは違って"]},{"code":401,"indent":0,"parameters":["はっきりとしたくすぐったさを肌に伝えてくる。"]},{"code":250,"indent":0,"parameters":[{"name":"Wind3","volume":90,"pitch":100,"pan":0}]},{"code":224,"indent":0,"parameters":[[255,255,255,170],30,false]},{"code":225,"indent":0,"parameters":[9,9,30,false]},{"code":101,"indent":0,"parameters":["",0,1,2]},{"code":401,"indent":0,"parameters":["シャノン"]},{"code":401,"indent":0,"parameters":["「ひゃっはははははははは！！？\\."]},{"code":401,"indent":0,"parameters":["　くすぐったいですぅぅううううっ！！\\."]},{"code":401,"indent":0,"parameters":["　ひゃひぃ！！？\\.　そんなところまでぇぇっへへへ！！？」"]},{"code":101,"indent":0,"parameters":["",0,1,2]},{"code":401,"indent":0,"parameters":["全てをさらけ出した恥ずかしいポーズのせいで"]},{"code":401,"indent":0,"parameters":["腋の下、お腹、太もも、足の裏といった弱点を"]},{"code":401,"indent":0,"parameters":["何一つ守れず、すべてがくすぐりの餌食となるのだ。"]},{"code":250,"indent":0,"parameters":[{"name":"Wind3","volume":90,"pitch":100,"pan":0}]},{"code":224,"indent":0,"parameters":[[255,255,255,170],30,false]},{"code":225,"indent":0,"parameters":[9,9,30,false]},{"code":101,"indent":0,"parameters":["",0,1,2]},{"code":401,"indent":0,"parameters":["シャノン"]},{"code":401,"indent":0,"parameters":["「あっははははははははは！！！\\."]},{"code":401,"indent":0,"parameters":["　やめてぇぇえええっへへへへへへへ！！\\."]},{"code":401,"indent":0,"parameters":["　こちょこちょ嫌ですぅぅううううううっ！！」"]},{"code":101,"indent":0,"parameters":["",0,1,2]},{"code":401,"indent":0,"parameters":["このマジックハンドは"]},{"code":401,"indent":0,"parameters":["ただ対象に張りついてくすぐるというシンプルなもので"]},{"code":401,"indent":0,"parameters":["単価は安く、大量に購入されることもある。"]},{"code":101,"indent":0,"parameters":["",0,1,2]},{"code":401,"indent":0,"parameters":["数が多いせいで、詰まってしまい"]},{"code":401,"indent":0,"parameters":["少しずつしか出てきていなかったが"]},{"code":401,"indent":0,"parameters":["荷物の中には起動状態になった"]},{"code":401,"indent":0,"parameters":["マジックハンドがまだまだ大量に潜んでいるのだ。"]},{"code":101,"indent":0,"parameters":["",0,1,2]},{"code":401,"indent":0,"parameters":["そしてその詰まりも一時的なもの。"]},{"code":401,"indent":0,"parameters":["開放されたマジックハンドたちは"]},{"code":401,"indent":0,"parameters":["ダムが決壊するかのように勢いよく"]},{"code":401,"indent":0,"parameters":["シャノンへと流れ込む……！"]},{"code":117,"indent":0,"parameters":[7]},{"code":231,"indent":0,"parameters":[1,"イベントd",1,0,428,294,100,100,255,0]},{"code":250,"indent":0,"parameters":[{"name":"Wind3","volume":90,"pitch":100,"pan":0}]},{"code":224,"indent":0,"parameters":[[255,255,255,170],30,false]},{"code":225,"indent":0,"parameters":[9,9,30,false]},{"code":122,"indent":0,"parameters":[12,12,0,0,428]},{"code":122,"indent":0,"parameters":[13,13,0,0,294]},{"code":121,"indent":0,"parameters":[2,2,0]},{"code":122,"indent":0,"parameters":[15,15,0,0,217]},{"code":122,"indent":0,"parameters":[16,16,0,0,96]},{"code":117,"indent":0,"parameters":[6]},{"code":101,"indent":0,"parameters":["",0,1,2]},{"code":401,"indent":0,"parameters":["シャノン"]},{"code":401,"indent":0,"parameters":["「ぎゃははははははははぁぁあああ！！？\\."]},{"code":401,"indent":0,"parameters":["　お、\\.おおすぎますぅぅうううっ！！\\."]},{"code":401,"indent":0,"parameters":["　だれかとめてぇぇええええっひぇっへへへへへ！！」"]},{"code":101,"indent":0,"parameters":["",0,1,2]},{"code":401,"indent":0,"parameters":["体中どこもかしこもマジックハンドだらけで"]},{"code":401,"indent":0,"parameters":["胸や股間までもがくすぐられるという始末。"]},{"code":401,"indent":0,"parameters":["どこに意識をやっても「くすぐったい」からは逃れられない。"]},{"code":250,"indent":0,"parameters":[{"name":"Wind3","volume":90,"pitch":100,"pan":0}]},{"code":224,"indent":0,"parameters":[[255,255,255,170],30,false]},{"code":225,"indent":0,"parameters":[9,9,30,false]},{"code":101,"indent":0,"parameters":["",0,1,2]},{"code":401,"indent":0,"parameters":["シャノン"]},{"code":401,"indent":0,"parameters":["「あっひゃははははははははは！！！\\."]},{"code":401,"indent":0,"parameters":["　そんなところだめぇぇえええっへへへへへ！！？\\."]},{"code":401,"indent":0,"parameters":["　もう限界ですぅぅうううううううっ！！」"]},{"code":101,"indent":0,"parameters":["",0,1,2]},{"code":401,"indent":0,"parameters":["何を言おうと叫ぼうと無機質なトラップには届かない。"]},{"code":401,"indent":0,"parameters":["エネルギーの切れるまで対象をくすぐり続けるだけだ。"]},{"code":250,"indent":0,"parameters":[{"name":"Wind3","volume":90,"pitch":100,"pan":0}]},{"code":224,"indent":0,"parameters":[[255,255,255,170],30,false]},{"code":225,"indent":0,"parameters":[9,9,30,false]},{"code":101,"indent":0,"parameters":["",0,1,2]},{"code":401,"indent":0,"parameters":["シャノン"]},{"code":401,"indent":0,"parameters":["「びゃっははははははひぇっへへへへへ！！\\."]},{"code":401,"indent":0,"parameters":["　ほ、\\.ほんとにもう……\\.　ダメですぅぅ……っ！！　"]},{"code":401,"indent":0,"parameters":["　ああっ、\\.ああああああ……っ！！」"]},{"code":117,"indent":0,"parameters":[7]},{"code":231,"indent":0,"parameters":[1,"イベントe",1,0,428,294,100,100,255,0]},{"code":250,"indent":0,"parameters":[{"name":"Wind3","volume":90,"pitch":100,"pan":0}]},{"code":250,"indent":0,"parameters":[{"name":"Liquid","volume":90,"pitch":100,"pan":0}]},{"code":250,"indent":0,"parameters":[{"name":"Liquid","volume":90,"pitch":100,"pan":0}]},{"code":224,"indent":0,"parameters":[[255,255,255,170],30,false]},{"code":225,"indent":0,"parameters":[9,9,30,false]},{"code":122,"indent":0,"parameters":[12,12,0,0,428]},{"code":122,"indent":0,"parameters":[13,13,0,0,294]},{"code":121,"indent":0,"parameters":[2,2,0]},{"code":122,"indent":0,"parameters":[15,15,0,0,217]},{"code":122,"indent":0,"parameters":[16,16,0,0,96]},{"code":117,"indent":0,"parameters":[6]},{"code":101,"indent":0,"parameters":["",0,1,2]},{"code":401,"indent":0,"parameters":["シャノン"]},{"code":401,"indent":0,"parameters":["「ふぁぁああああああっ……！！！\\."]},{"code":401,"indent":0,"parameters":["　～～～～～～～～～～～っ！！」"]},{"code":101,"indent":0,"parameters":["",0,1,2]},{"code":401,"indent":0,"parameters":["マジックハンドの無慈悲なこちょこちょ攻撃に"]},{"code":401,"indent":0,"parameters":["シャノンは恥ずかしいポーズのまま無様に失禁してしまう。"]},{"code":401,"indent":0,"parameters":["おしっこは下着をぐっしょりと濡らして"]},{"code":401,"indent":0,"parameters":["足元には大きな水たまりができあがる。"]},{"code":250,"indent":0,"parameters":[{"name":"Wind3","volume":90,"pitch":100,"pan":0}]},{"code":224,"indent":0,"parameters":[[255,255,255,170],30,false]},{"code":225,"indent":0,"parameters":[9,9,30,false]},{"code":101,"indent":0,"parameters":["",0,1,2]},{"code":401,"indent":0,"parameters":["シャノン"]},{"code":401,"indent":0,"parameters":["「ひっ、\\.ひひひひ……！\\."]},{"code":401,"indent":0,"parameters":["　こんなところで、お漏らしなんて……っ\\."]},{"code":401,"indent":0,"parameters":["　あひひひっへっへへへへへ……！」"]},{"code":101,"indent":0,"parameters":["",0,1,2]},{"code":401,"indent":0,"parameters":["股間はびしょびしょで、体は汗だく"]},{"code":401,"indent":0,"parameters":["顔も涙やよだれでぐしょぐしょ……"]},{"code":401,"indent":0,"parameters":["こんなにも情けない姿を晒しているというのに"]},{"code":401,"indent":0,"parameters":["マジックハンドは一向にくすぐりをやめてはくれない。"]},{"code":250,"indent":0,"parameters":[{"name":"Wind3","volume":90,"pitch":100,"pan":0}]},{"code":224,"indent":0,"parameters":[[255,255,255,170],30,false]},{"code":225,"indent":0,"parameters":[9,9,30,false]},{"code":101,"indent":0,"parameters":["",0,1,2]},{"code":401,"indent":0,"parameters":["シャノン"]},{"code":401,"indent":0,"parameters":["「あっひぇへへへへへへへ……！\\."]},{"code":401,"indent":0,"parameters":["　ひふふふふひぇっへへへへへへ！！\\."]},{"code":401,"indent":0,"parameters":["　もう許してよぉぉおおおおおおっ！！」"]},{"code":250,"indent":0,"parameters":[{"name":"Wind3","volume":90,"pitch":100,"pan":0}]},{"code":224,"indent":0,"parameters":[[255,255,255,170],30,false]},{"code":225,"indent":0,"parameters":[9,9,30,false]},{"code":230,"indent":0,"parameters":[60]},{"code":250,"indent":0,"parameters":[{"name":"Wind3","volume":90,"pitch":100,"pan":0}]},{"code":224,"indent":0,"parameters":[[255,255,255,170],30,false]},{"code":225,"indent":0,"parameters":[9,9,30,false]},{"code":230,"indent":0,"parameters":[60]},{"code":250,"indent":0,"parameters":[{"name":"Wind3","volume":90,"pitch":100,"pan":0}]},{"code":224,"indent":0,"parameters":[[255,255,255,170],30,false]},{"code":225,"indent":0,"parameters":[9,9,30,false]},{"code":230,"indent":0,"parameters":[60]},{"code":101,"indent":0,"parameters":["",0,1,2]},{"code":401,"indent":0,"parameters":["その後、たまたま通りかかったツインテールの少女に"]},{"code":401,"indent":0,"parameters":["救出されるまで"]},{"code":401,"indent":0,"parameters":["シャロンは醜態を晒し続けるのだった……"]},{"code":117,"indent":0,"parameters":[7]},{"code":235,"indent":0,"parameters":[1]},{"code":0,"indent":0,"parameters":[]}],"name":"イベント","switchId":1,"trigger":0},
{"id":12,"list":[{"code":250,"indent":0,"parameters":[{"name":"Reflection","volume":90,"pitch":100,"pan":0}]},{"code":121,"indent":0,"parameters":[7,7,0]},{"code":356,"indent":0,"parameters":["D_TEXT \\C[17]GUARD 32"]},{"code":231,"indent":0,"parameters":[3,"",1,0,600,29,100,100,255,0]},{"code":214,"indent":0,"parameters":[]},{"code":0,"indent":0,"parameters":[]}],"name":"盾","switchId":1,"trigger":0},
{"id":13,"list":[{"code":121,"indent":0,"parameters":[10,10,1]},{"code":235,"indent":0,"parameters":[1]},{"code":235,"indent":0,"parameters":[2]},{"code":235,"indent":0,"parameters":[3]},{"code":221,"indent":0,"parameters":[]},{"code":211,"indent":0,"parameters":[1]},{"code":356,"indent":0,"parameters":["オリジナルタイマー 取得 秒 1"]},{"code":356,"indent":0,"parameters":["オリジナルタイマー 取得 分 4"]},{"code":356,"indent":0,"parameters":["オリジナルタイマー 取得 時 6"]},{"code":356,"indent":0,"parameters":["オリジナルタイマー 停止"]},{"code":122,"indent":0,"parameters":[4,4,3,0,60]},{"code":122,"indent":0,"parameters":[6,6,3,0,3600]},{"code":122,"indent":0,"parameters":[1,1,1,1,4]},{"code":122,"indent":0,"parameters":[1,1,1,1,6]},{"code":122,"indent":0,"parameters":[5,5,0,0,300]},{"code":122,"indent":0,"parameters":[5,5,2,1,1]},{"code":111,"indent":0,"parameters":[1,5,0,0,2]},{"code":122,"indent":1,"parameters":[5,5,0,0,0]},{"code":0,"indent":1,"parameters":[]},{"code":412,"indent":0,"parameters":[]},{"code":122,"indent":0,"parameters":[5,5,3,0,100]},{"code":111,"indent":0,"parameters":[1,7,0,0,0]},{"code":122,"indent":1,"parameters":[19,19,0,0,10000]},{"code":0,"indent":1,"parameters":[]},{"code":412,"indent":0,"parameters":[]},{"code":111,"indent":0,"parameters":[1,7,0,1,0]},{"code":122,"indent":1,"parameters":[19,19,0,0,3000]},{"code":0,"indent":1,"parameters":[]},{"code":412,"indent":0,"parameters":[]},{"code":111,"indent":0,"parameters":[1,7,0,2,0]},{"code":122,"indent":1,"parameters":[19,19,0,0,0]},{"code":0,"indent":1,"parameters":[]},{"code":412,"indent":0,"parameters":[]},{"code":101,"indent":0,"parameters":["",0,0,2]},{"code":401,"indent":0,"parameters":["暫定配達ポイント　　　\\V[8]"]},{"code":401,"indent":0,"parameters":["タイムボーナス　　 　+\\V[5]"]},{"code":401,"indent":0,"parameters":["服装ボーナス　　　　 +\\V[19]　"]},{"code":122,"indent":0,"parameters":[8,8,1,1,5]},{"code":122,"indent":0,"parameters":[8,8,1,1,19]},{"code":111,"indent":0,"parameters":[1,8,1,9,1]},{"code":122,"indent":1,"parameters":[11,11,0,1,10]},{"code":122,"indent":1,"parameters":[10,10,0,1,9]},{"code":122,"indent":1,"parameters":[9,9,0,1,8]},{"code":119,"indent":1,"parameters":["skip"]},{"code":0,"indent":1,"parameters":[]},{"code":412,"indent":0,"parameters":[]},{"code":111,"indent":0,"parameters":[1,8,1,10,1]},{"code":122,"indent":1,"parameters":[11,11,0,1,10]},{"code":122,"indent":1,"parameters":[10,10,0,1,8]},{"code":119,"indent":1,"parameters":["skip"]},{"code":0,"indent":1,"parameters":[]},{"code":412,"indent":0,"parameters":[]},{"code":111,"indent":0,"parameters":[1,8,1,11,1]},{"code":122,"indent":1,"parameters":[11,11,0,1,8]},{"code":119,"indent":1,"parameters":["skip"]},{"code":0,"indent":1,"parameters":[]},{"code":412,"indent":0,"parameters":[]},{"code":118,"indent":0,"parameters":["skip"]},{"code":101,"indent":0,"parameters":["",0,0,2]},{"code":401,"indent":0,"parameters":["最終配達ポイント　　\\V[8]"]},{"code":401,"indent":0,"parameters":["１位　\\V[9]"]},{"code":401,"indent":0,"parameters":["２位　\\V[10]"]},{"code":401,"indent":0,"parameters":["３位　\\V[11]"]},{"code":250,"indent":0,"parameters":[{"name":"Sound4","volume":90,"pitch":100,"pan":0}]},{"code":111,"indent":0,"parameters":[1,8,0,80000,1]},{"code":121,"indent":1,"parameters":[8,8,0]},{"code":121,"indent":1,"parameters":[9,9,0]},{"code":101,"indent":1,"parameters":["",0,0,2]},{"code":401,"indent":1,"parameters":["ランク　ＳＳ"]},{"code":401,"indent":1,"parameters":["神速配達員\\|\\|\\|\\|"]},{"code":119,"indent":1,"parameters":["判定"]},{"code":0,"indent":1,"parameters":[]},{"code":412,"indent":0,"parameters":[]},{"code":111,"indent":0,"parameters":[1,8,0,50000,1]},{"code":121,"indent":1,"parameters":[8,8,0]},{"code":121,"indent":1,"parameters":[9,9,0]},{"code":101,"indent":1,"parameters":["",0,0,2]},{"code":401,"indent":1,"parameters":["ランク　Ｓ"]},{"code":401,"indent":1,"parameters":["音速配達員\\|\\|\\|\\|"]},{"code":119,"indent":1,"parameters":["判定"]},{"code":0,"indent":1,"parameters":[]},{"code":412,"indent":0,"parameters":[]},{"code":111,"indent":0,"parameters":[1,8,0,30000,1]},{"code":101,"indent":1,"parameters":["",0,0,2]},{"code":401,"indent":1,"parameters":["ランク　Ａ"]},{"code":401,"indent":1,"parameters":["高速配達員\\|\\|\\|\\|"]},{"code":119,"indent":1,"parameters":["判定"]},{"code":0,"indent":1,"parameters":[]},{"code":412,"indent":0,"parameters":[]},{"code":101,"indent":0,"parameters":["",0,0,2]},{"code":401,"indent":0,"parameters":["ランク　Ｂ"]},{"code":401,"indent":0,"parameters":["普通の配達員\\|\\|\\|\\|"]},{"code":118,"indent":0,"parameters":["判定"]},{"code":122,"indent":0,"parameters":[7,7,0,0,0]},{"code":121,"indent":0,"parameters":[7,7,1]},{"code":121,"indent":0,"parameters":[1,1,1]},{"code":122,"indent":0,"parameters":[17,17,0,0,0]},{"code":122,"indent":0,"parameters":[18,18,0,0,0]},{"code":122,"indent":0,"parameters":[8,8,0,0,0]},{"code":322,"indent":0,"parameters":[1,"シャノン",0,"シャノン",0,""]},{"code":205,"indent":0,"parameters":[-1,{"list":[{"code":36,"indent":null},{"code":29,"parameters":[4],"indent":null},{"code":0}],"repeat":false,"skippable":false,"wait":true}]},{"code":505,"indent":0,"parameters":[{"code":36,"indent":null}]},{"code":505,"indent":0,"parameters":[{"code":29,"parameters":[4],"indent":null}]},{"code":101,"indent":0,"parameters":["",0,0,2]},{"code":401,"indent":0,"parameters":["イベントシーンを見ますか？"]},{"code":401,"indent":0,"parameters":["（配達ポイント５００００以上でくすぐりイベント"]},{"code":401,"indent":0,"parameters":["　それ以下なら通常イベント）"]},{"code":102,"indent":0,"parameters":[["はい","いいえ"],1,0,2,0]},{"code":402,"indent":0,"parameters":[0,"はい"]},{"code":201,"indent":1,"parameters":[0,3,21,31,8,0]},{"code":0,"indent":1,"parameters":[]},{"code":402,"indent":0,"parameters":[1,"いいえ"]},{"code":121,"indent":1,"parameters":[8,8,1]},{"code":201,"indent":1,"parameters":[0,5,8,8,2,0]},{"code":0,"indent":1,"parameters":[]},{"code":404,"indent":0,"parameters":[]},{"code":222,"indent":0,"parameters":[]},{"code":0,"indent":0,"parameters":[]}],"name":"スコア計算","switchId":1,"trigger":0},
{"id":14,"list":[{"code":122,"indent":0,"parameters":[2,2,0,3,5,-1,0]},{"code":111,"indent":0,"parameters":[11,"left"]},{"code":111,"indent":1,"parameters":[1,2,0,0,5]},{"code":205,"indent":2,"parameters":[-1,{"list":[{"code":2,"indent":null},{"code":0}],"repeat":false,"skippable":true,"wait":true}]},{"code":505,"indent":2,"parameters":[{"code":2,"indent":null}]},{"code":119,"indent":2,"parameters":["skip"]},{"code":0,"indent":2,"parameters":[]},{"code":412,"indent":1,"parameters":[]},{"code":0,"indent":1,"parameters":[]},{"code":412,"indent":0,"parameters":[]},{"code":111,"indent":0,"parameters":[11,"right"]},{"code":111,"indent":1,"parameters":[1,2,0,4,5]},{"code":205,"indent":2,"parameters":[-1,{"list":[{"code":3,"indent":null},{"code":0}],"repeat":false,"skippable":true,"wait":true}]},{"code":505,"indent":2,"parameters":[{"code":3,"indent":null}]},{"code":119,"indent":2,"parameters":["skip"]},{"code":0,"indent":2,"parameters":[]},{"code":412,"indent":1,"parameters":[]},{"code":0,"indent":1,"parameters":[]},{"code":412,"indent":0,"parameters":[]},{"code":204,"indent":0,"parameters":[8,1,6]},{"code":205,"indent":0,"parameters":[-1,{"list":[{"code":4,"indent":null},{"code":0}],"repeat":false,"skippable":true,"wait":false}]},{"code":505,"indent":0,"parameters":[{"code":4,"indent":null}]},{"code":118,"indent":0,"parameters":["skip"]},{"code":0,"indent":0,"parameters":[]}],"name":"左右移動","switchId":10,"trigger":2},
{"id":15,"list":[{"code":0,"indent":0,"parameters":[]}],"name":"","switchId":1,"trigger":0}
]